{
  "objectInfo" : {
    "id" : "7ODk0JQgmmPeNQYR7pkXQx",
    "name" : "TF_Sales_Analytics_Staging",
    "type" : "TASKFLOW",
    "metadata" : {
      "modelVersion" : {
        "major" : 1,
        "minor" : 0
      },
      "repoInfo" : {
        "repoHandle" : "RMloVVVVVVVVVVV-gt-55052137-2021-05-04T12:48:13.704Z::tf.xml"
      },
      "contextAttributes" : null,
      "additionalInfo" : {
        "description" : "",
        "contentType" : "application/json; charset=utf-8",
        "documentState" : "VALID"
      }
    }
  },
  "dataFileExtension" : "xml",
  "objectRefs" : [ {
    "id" : "2WN9Snn8pIkgMmF5UsLXq1",
    "name" : "mct_Stg_Lead_Extract",
    "type" : "MTT",
    "metadata" : {
      "modelVersion" : {
        "major" : 0,
        "minor" : 0
      },
      "repoInfo" : {
        "repoHandle" : "01037X0Z0000000004W9"
      },
      "contextAttributes" : [ {
        "name" : "id",
        "value" : "@1"
      } ],
      "additionalInfo" : {
        "description" : "",
        "contentType" : "JSON",
        "documentState" : "VALID"
      }
    },
    "path" : "/Explore/PARAMETER_INFOFISCUS/Sales_Analytics"
  }, {
    "id" : "kN7buXfqecpdM39TuKYcOx",
    "name" : "Mtt_Account_Stg_Extract",
    "type" : "MTT",
    "metadata" : {
      "modelVersion" : {
        "major" : 0,
        "minor" : 0
      },
      "repoInfo" : {
        "repoHandle" : "01037X0Z0000000004W7"
      },
      "contextAttributes" : [ {
        "name" : "id",
        "value" : "@1"
      } ],
      "additionalInfo" : {
        "description" : "",
        "contentType" : "JSON",
        "documentState" : "VALID"
      }
    },
    "path" : "/Explore/PARAMETER_INFOFISCUS/Sales_Analytics"
  }, {
    "id" : "eA50W8jOxmCg8SnImpWzmQ",
    "name" : "Mtt_Product_Stg_Extract",
    "type" : "MTT",
    "metadata" : {
      "modelVersion" : {
        "major" : 0,
        "minor" : 0
      },
      "repoInfo" : {
        "repoHandle" : "01037X0Z0000000004WA"
      },
      "contextAttributes" : [ {
        "name" : "id",
        "value" : "@1"
      } ],
      "additionalInfo" : {
        "description" : "",
        "contentType" : "JSON",
        "documentState" : "VALID"
      }
    },
    "path" : "/Explore/PARAMETER_INFOFISCUS/Sales_Analytics"
  }, {
    "id" : "2YY2dOAcruTgzu8wT59k0r",
    "name" : "m_Runid _table",
    "type" : "MTT",
    "metadata" : {
      "modelVersion" : {
        "major" : 0,
        "minor" : 0
      },
      "repoInfo" : {
        "repoHandle" : "01037X0Z0000000004W5"
      },
      "contextAttributes" : [ {
        "name" : "id",
        "value" : "@1"
      } ],
      "additionalInfo" : {
        "description" : "",
        "contentType" : "JSON",
        "documentState" : "VALID"
      }
    },
    "path" : "/Explore/PARAMETER_INFOFISCUS/Sales_Analytics"
  }, {
    "id" : "4aews4JCqE5dHTgLEwkM6N",
    "name" : "Mtt_Opportunity_Stg_Extract",
    "type" : "MTT",
    "metadata" : {
      "modelVersion" : {
        "major" : 0,
        "minor" : 0
      },
      "repoInfo" : {
        "repoHandle" : "01037X0Z0000000004WD"
      },
      "contextAttributes" : [ {
        "name" : "id",
        "value" : "@1"
      } ],
      "additionalInfo" : {
        "description" : "",
        "contentType" : "JSON",
        "documentState" : "VALID"
      }
    },
    "path" : "/Explore/PARAMETER_INFOFISCUS/Sales_Analytics"
  }, {
    "id" : "dszoZdVcNcTgNb25DyZJob",
    "name" : "mtt_landing_Stg_Contract_Extract",
    "type" : "MTT",
    "metadata" : {
      "modelVersion" : {
        "major" : 0,
        "minor" : 0
      },
      "repoInfo" : {
        "repoHandle" : "01037X0Z0000000004WE"
      },
      "contextAttributes" : [ {
        "name" : "id",
        "value" : "@1"
      } ],
      "additionalInfo" : {
        "description" : "",
        "contentType" : "JSON",
        "documentState" : "VALID"
      }
    },
    "path" : "/Explore/PARAMETER_INFOFISCUS/Sales_Analytics"
  }, {
    "id" : "6butGJZqOf6g7bHX90nyoz",
    "name" : "mtt_landing_Stg_Campaign_Extract",
    "type" : "MTT",
    "metadata" : {
      "modelVersion" : {
        "major" : 0,
        "minor" : 0
      },
      "repoInfo" : {
        "repoHandle" : "01037X0Z0000000004WB"
      },
      "contextAttributes" : [ {
        "name" : "id",
        "value" : "@1"
      } ],
      "additionalInfo" : {
        "description" : "",
        "contentType" : "JSON",
        "documentState" : "VALID"
      }
    },
    "path" : "/Explore/PARAMETER_INFOFISCUS/Sales_Analytics"
  }, {
    "id" : "5CvxEBUrJmdjB3GbcnWKoC",
    "name" : "mtt_landing_Stg_Contact_Extract",
    "type" : "MTT",
    "metadata" : {
      "modelVersion" : {
        "major" : 0,
        "minor" : 0
      },
      "repoInfo" : {
        "repoHandle" : "01037X0Z0000000004WC"
      },
      "contextAttributes" : [ {
        "name" : "id",
        "value" : "@1"
      } ],
      "additionalInfo" : {
        "description" : "",
        "contentType" : "JSON",
        "documentState" : "VALID"
      }
    },
    "path" : "/Explore/PARAMETER_INFOFISCUS/Sales_Analytics"
  }, {
    "id" : "6YWp9jTYNGng2jujjIvVMt",
    "name" : "Mtt_User_Stg_Extract",
    "type" : "MTT",
    "metadata" : {
      "modelVersion" : {
        "major" : 0,
        "minor" : 0
      },
      "repoInfo" : {
        "repoHandle" : "01037X0Z0000000004W8"
      },
      "contextAttributes" : [ {
        "name" : "id",
        "value" : "@1"
      } ],
      "additionalInfo" : {
        "description" : "",
        "contentType" : "JSON",
        "documentState" : "VALID"
      }
    },
    "path" : "/Explore/PARAMETER_INFOFISCUS/Sales_Analytics"
  }, {
    "id" : "3EW7oz17iA7jAazKSZxpE7",
    "name" : "Mtt_Pricebook_Stg_Extract",
    "type" : "MTT",
    "metadata" : {
      "modelVersion" : {
        "major" : 0,
        "minor" : 0
      },
      "repoInfo" : {
        "repoHandle" : "01037X0Z0000000004W6"
      },
      "contextAttributes" : [ {
        "name" : "id",
        "value" : "@1"
      } ],
      "additionalInfo" : {
        "description" : "",
        "contentType" : "JSON",
        "documentState" : "VALID"
      }
    },
    "path" : "/Explore/PARAMETER_INFOFISCUS/Sales_Analytics"
  } ]
}